MCRP/__init__.py
MCRP/dgi.py
MCRP/iautil.py
MCRP/mcrp.py
MCRP/mcwp.py
MCRP/tcproxy.py
MCRP/util.py
MCRP-0.1.10.dist-info/LICENSE
MCRP-0.1.10.dist-info/METADATA
MCRP-0.1.10.dist-info/WHEEL
MCRP-0.1.10.dist-info/entry_points.txt
MCRP-0.1.10.dist-info/top_level.txt
MCRP-0.1.10.dist-info/RECORD
