Metadata-Version: 2.1
Name: MCRP
Version: 0.1.10
Summary: Minecraft MITM proxy with function of rewriting packets, written in pure Python 3
Home-page: https://gitlab.com/seeklay/MCRP
Author: seeklay
Author-email: rudeboy@seeklay.icu
License: GNU General Public License v3.0
Download-URL: https://gitlab.com/seeklay/MCRP
Platform: OS Independent
Classifier: Development Status :: 4 - Beta
Classifier: Environment :: Console
Classifier: Programming Language :: Python :: 3.7
Classifier: Programming Language :: Python :: Implementation :: CPython
Classifier: Programming Language :: Python :: Implementation :: PyPy
Classifier: Intended Audience :: End Users/Desktop
Classifier: Natural Language :: English
Classifier: License :: OSI Approved :: GNU General Public License v3 (GPLv3)
Classifier: Operating System :: OS Independent
Classifier: Topic :: Internet
Requires-Dist: cubelib (>=1.0.3-pre.1)
Requires-Dist: ruamel.yaml (==0.17.21)
